raster_barcode/__init__.py
raster_barcode/barcode.py
raster_barcode/barplot.py
raster_barcode/bin_state.py
raster_barcode/libbarpy.pyd
raster_barcode/libbarpy.pyi
raster_barcode-1.0.3.dist-info/LICENSE
raster_barcode-1.0.3.dist-info/METADATA
raster_barcode-1.0.3.dist-info/WHEEL
raster_barcode-1.0.3.dist-info/top_level.txt
raster_barcode-1.0.3.dist-info/RECORD
