Metadata-Version: 2.1
Name: raster_barcode
Version: 1.0.3
Summary: Python wrapper for the Barcode library.
Home-page: https://github.com/Noremos/Barcode
Author: Art A
Author-email: your.email@example.com
License: MIT
Classifier: Programming Language :: Python :: 3.13
Classifier: Operating System :: OS Independent
Classifier: Operating System :: Microsoft :: Windows
Classifier: Operating System :: POSIX :: Linux
Classifier: Operating System :: MacOS
Requires-Python: ==3.13
License-File: LICENSE
Requires-Dist: numpy
Requires-Dist: matplotlib
